aiminify/__init__.py
aiminify-0.0.2.dist-info/METADATA
aiminify-0.0.2.dist-info/WHEEL
aiminify-0.0.2.dist-info/top_level.txt
aiminify-0.0.2.dist-info/RECORD
