Metadata-Version: 2.1
Name: aiminify
Version: 0.0.2
Summary: Just create the package
Home-page: https://github.com/
Author: Pablo Perez de Ciriza
Author-email: pabloperezdeciriza@stapesit.com
License: MIT
